README.rst
setup.py
autoarg/__init__.py
autoarg/parser.py
autoarg.egg-info/PKG-INFO
autoarg.egg-info/SOURCES.txt
autoarg.egg-info/dependency_links.txt
autoarg.egg-info/top_level.txt